{
    "date": "2019-12-07T23:14:53Z",
    "git": {
        "head_sha1": "05df0ce89b078589e3a0eca9db3a43753174a184",
        "is_dirty": true,
        "retrieved_state": true
    },
    "instances": [
        {
            "greedy": {
                "solution_final": {
                    "problem": {
                        "name": "NRH.5",
                        "points_number": 1000,
                        "reduced": false,
                        "subsets_number": 10000
                    },
                    "selected_subsets": [
                        105,
                        114,
                        134,
                        217,
                        230,
                        274,
                        815,
                        926,
                        1314,
                        1315,
                        1527,
                        1533,
                        1725,
                        2030,
                        2130,
                        2333,
                        2617,
                        2839,
                        3128,
                        4354,
                        4442,
                        4852,
                        5051,
                        5242,
                        5445,
                        5905,
                        6905,
                        6999,
                        7090,
                        7873,
                        8075,
                        8284,
                        9110,
                        9386,
                        9605,
                        9609
                    ]
                },
                "time": 0.01683328
            },
            "instance": {
                "name": "NRH.5",
                "points_number": 1000,
                "reduced": false,
                "subsets_number": 10000
            },
            "memetic": [
                {
                    "crossover_operator": "subproblem_greedy",
                    "ended_at": {
                        "generation": 100,
                        "rwls_cumulative_position": {
                            "steps": 30000000,
                            "time": 4924.01369088
                        },
                        "time": 2476.957434112
                    },
                    "found_at": {
                        "generation": 1,
                        "rwls_cumulative_position": {
                            "steps": 447629,
                            "time": 71.81804416
                        },
                        "time": 48.506363648
                    },
                    "points_weights_final": [
                        2579,
                        2546,
                        2419,
                        2181,
                        2450,
                        1792,
                        2480,
                        2499,
                        2602,
                        2326,
                        2486,
                        2868,
                        2475,
                        2580,
                        2532,
                        2342,
                        2595,
                        2472,
                        2578,
                        2498,
                        2545,
                        2488,
                        2388,
                        2343,
                        2178,
                        2500,
                        2100,
                        2415,
                        2747,
                        2306,
                        2257,
                        2534,
                        2646,
                        2636,
                        2264,
                        2202,
                        2731,
                        2433,
                        2474,
                        2419,
                        2816,
                        2543,
                        2788,
                        2761,
                        2404,
                        2467,
                        2500,
                        2758,
                        2698,
                        2437,
                        2427,
                        2466,
                        2661,
                        2736,
                        3019,
                        1829,
                        2261,
                        2335,
                        2770,
                        2835,
                        2603,
                        2705,
                        2517,
                        2762,
                        2407,
                        2219,
                        2392,
                        2516,
                        2309,
                        2884,
                        2128,
                        1987,
                        2699,
                        2464,
                        2479,
                        2453,
                        2593,
                        2608,
                        2496,
                        2772,
                        2577,
                        2513,
                        2596,
                        2574,
                        2726,
                        2396,
                        2626,
                        2467,
                        2631,
                        2899,
                        2892,
                        2521,
                        2482,
                        2829,
                        2370,
                        2309,
                        2767,
                        2225,
                        2518,
                        2448,
                        2756,
                        1872,
                        2486,
                        2664,
                        2504,
                        2682,
                        2669,
                        2879,
                        2596,
                        2704,
                        2757,
                        2580,
                        2238,
                        2655,
                        2538,
                        2087,
                        2451,
                        2452,
                        2731,
                        2495,
                        2490,
                        2682,
                        2609,
                        2516,
                        2274,
                        2349,
                        2810,
                        2609,
                        2366,
                        2360,
                        2458,
                        2571,
                        2461,
                        2678,
                        2635,
                        2176,
                        2471,
                        2304,
                        2448,
                        2703,
                        2416,
                        2648,
                        2676,
                        2723,
                        1867,
                        2713,
                        2603,
                        2703,
                        2316,
                        2261,
                        2744,
                        2188,
                        2556,
                        2160,
                        2465,
                        2264,
                        2512,
                        2511,
                        2571,
                        2475,
                        2749,
                        2808,
                        2693,
                        2377,
                        2745,
                        2427,
                        2555,
                        2497,
                        2732,
                        2498,
                        2765,
                        2707,
                        2261,
                        2656,
                        2669,
                        2224,
                        2494,
                        2584,
                        2690,
                        1873,
                        2807,
                        2022,
                        2718,
                        2625,
                        2567,
                        2209,
                        2488,
                        2494,
                        2816,
                        2214,
                        2829,
                        2424,
                        2609,
                        2493,
                        2547,
                        2510,
                        2823,
                        2608,
                        2428,
                        2430,
                        2540,
                        2635,
                        2664,
                        2682,
                        2354,
                        2700,
                        2428,
                        2550,
                        2581,
                        2582,
                        2893,
                        2615,
                        2388,
                        2736,
                        2475,
                        2814,
                        2522,
                        2756,
                        2287,
                        2463,
                        2233,
                        2753,
                        2341,
                        2275,
                        2734,
                        2690,
                        2702,
                        2366,
                        2540,
                        2299,
                        2661,
                        2621,
                        2768,
                        2742,
                        2778,
                        2165,
                        2776,
                        2414,
                        2633,
                        2452,
                        2246,
                        2503,
                        2633,
                        2728,
                        2792,
                        2145,
                        2394,
                        2338,
                        2361,
                        2776,
                        2619,
                        2325,
                        2541,
                        2532,
                        2539,
                        2682,
                        2494,
                        2769,
                        2444,
                        2903,
                        2697,
                        2799,
                        2545,
                        2606,
                        2387,
                        2759,
                        2497,
                        2823,
                        2469,
                        2854,
                        2589,
                        2390,
                        2546,
                        2429,
                        2522,
                        2747,
                        2716,
                        2199,
                        2533,
                        2749,
                        2616,
                        2447,
                        2427,
                        2577,
                        2803,
                        2779,
                        2658,
                        2061,
                        2563,
                        2702,
                        2602,
                        2276,
                        2732,
                        2679,
                        2798,
                        2129,
                        2429,
                        2714,
                        2603,
                        2532,
                        2382,
                        2649,
                        2805,
                        2789,
                        2880,
                        2525,
                        2082,
                        2568,
                        2354,
                        2720,
                        2697,
                        2444,
                        2329,
                        2479,
                        2402,
                        2860,
                        2649,
                        2598,
                        2687,
                        2596,
                        2502,
                        2486,
                        2620,
                        2235,
                        2577,
                        2674,
                        2664,
                        2568,
                        2738,
                        2378,
                        2479,
                        2314,
                        2820,
                        2496,
                        2593,
                        2464,
                        2524,
                        2750,
                        2795,
                        2522,
                        2870,
                        2507,
                        2443,
                        2585,
                        2441,
                        2634,
                        2410,
                        2415,
                        2639,
                        2963,
                        2311,
                        2308,
                        2543,
                        2821,
                        2579,
                        2574,
                        2140,
                        2513,
                        2166,
                        2536,
                        2710,
                        2475,
                        2559,
                        2468,
                        2663,
                        2435,
                        2377,
                        2172,
                        2350,
                        2266,
                        2292,
                        2416,
                        2558,
                        2650,
                        2464,
                        2673,
                        2501,
                        2102,
                        2360,
                        2851,
                        2466,
                        2330,
                        2751,
                        2881,
                        2426,
                        2301,
                        2755,
                        2380,
                        2375,
                        2747,
                        2568,
                        2167,
                        2799,
                        2475,
                        2246,
                        2371,
                        2330,
                        2492,
                        2301,
                        2460,
                        2558,
                        2535,
                        2610,
                        2324,
                        2657,
                        2488,
                        2637,
                        2476,
                        2865,
                        2473,
                        2670,
                        2804,
                        2070,
                        2490,
                        2752,
                        2714,
                        2712,
                        2377,
                        2597,
                        2740,
                        2677,
                        2521,
                        2380,
                        2290,
                        2851,
                        2683,
                        2263,
                        2894,
                        2635,
                        2620,
                        2639,
                        2770,
                        2224,
                        3026,
                        2757,
                        2599,
                        2518,
                        2432,
                        2482,
                        2482,
                        2457,
                        2739,
                        2467,
                        2081,
                        2692,
                        2490,
                        2201,
                        2684,
                        2677,
                        2588,
                        2688,
                        2399,
                        2793,
                        2344,
                        2477,
                        2707,
                        2694,
                        2757,
                        2391,
                        2412,
                        2864,
                        2178,
                        2738,
                        2857,
                        2699,
                        2599,
                        2725,
                        2499,
                        2422,
                        2259,
                        2226,
                        2555,
                        2788,
                        2450,
                        2590,
                        2047,
                        2590,
                        2827,
                        2528,
                        2406,
                        2531,
                        2512,
                        2656,
                        2669,
                        2673,
                        2703,
                        1917,
                        2620,
                        2727,
                        2383,
                        2540,
                        2688,
                        2480,
                        2867,
                        2791,
                        2609,
                        2529,
                        2669,
                        2503,
                        2262,
                        2665,
                        2438,
                        2767,
                        2451,
                        2451,
                        2408,
                        2742,
                        2156,
                        2816,
                        2787,
                        2422,
                        2303,
                        2576,
                        2345,
                        2629,
                        2773,
                        2406,
                        2739,
                        2768,
                        2696,
                        2239,
                        2254,
                        2456,
                        2590,
                        2303,
                        2666,
                        2273,
                        2503,
                        2548,
                        2360,
                        2582,
                        2471,
                        2764,
                        2737,
                        2569,
                        2688,
                        2588,
                        2502,
                        2474,
                        2363,
                        2626,
                        2495,
                        2587,
                        2689,
                        2361,
                        2384,
                        2693,
                        2266,
                        2720,
                        2644,
                        2523,
                        2632,
                        2206,
                        2186,
                        2700,
                        2511,
                        2839,
                        2592,
                        2509,
                        2888,
                        2374,
                        2750,
                        2714,
                        2888,
                        2642,
                        2373,
                        2770,
                        2535,
                        2657,
                        2578,
                        2610,
                        2577,
                        2374,
                        2599,
                        2615,
                        2356,
                        2644,
                        2441,
                        2676,
                        2657,
                        2664,
                        2584,
                        2871,
                        2389,
                        2378,
                        2681,
                        2530,
                        2281,
                        2561,
                        2392,
                        3021,
                        2806,
                        2219,
                        2382,
                        2700,
                        2296,
                        2988,
                        2183,
                        2325,
                        2754,
                        2339,
                        2457,
                        2695,
                        2430,
                        2635,
                        2703,
                        2577,
                        2712,
                        3014,
                        2389,
                        2611,
                        2710,
                        2485,
                        2546,
                        2461,
                        2380,
                        2135,
                        2107,
                        2591,
                        2655,
                        2569,
                        2921,
                        2325,
                        2506,
                        2545,
                        2759,
                        2390,
                        2670,
                        2625,
                        2469,
                        2488,
                        2772,
                        2804,
                        2860,
                        2277,
                        2763,
                        2474,
                        2482,
                        2595,
                        2716,
                        2906,
                        2200,
                        2574,
                        2278,
                        2378,
                        2473,
                        2394,
                        2217,
                        2680,
                        2240,
                        2303,
                        2144,
                        2642,
                        2397,
                        2457,
                        2752,
                        2436,
                        2358,
                        2883,
                        2644,
                        2731,
                        2296,
                        2504,
                        2408,
                        2573,
                        2643,
                        2513,
                        2807,
                        2600,
                        2685,
                        2374,
                        2764,
                        2827,
                        2498,
                        2643,
                        2727,
                        2922,
                        2461,
                        2860,
                        2126,
                        2447,
                        2679,
                        2542,
                        2454,
                        2646,
                        2253,
                        2479,
                        2590,
                        2795,
                        2397,
                        2618,
                        2491,
                        2341,
                        2663,
                        2632,
                        2640,
                        2429,
                        2682,
                        2655,
                        2798,
                        2499,
                        2543,
                        2683,
                        2438,
                        2697,
                        2662,
                        2676,
                        2156,
                        2643,
                        2486,
                        2253,
                        2483,
                        2322,
                        2788,
                        2630,
                        2613,
                        2437,
                        2587,
                        2374,
                        2814,
                        2147,
                        2561,
                        2571,
                        2727,
                        2687,
                        2201,
                        2245,
                        2348,
                        2444,
                        2587,
                        2761,
                        2534,
                        2538,
                        2874,
                        2715,
                        2260,
                        2643,
                        2700,
                        2352,
                        2616,
                        2720,
                        2303,
                        2616,
                        2734,
                        2863,
                        2788,
                        2285,
                        2527,
                        2644,
                        2623,
                        2559,
                        2301,
                        2846,
                        1944,
                        2825,
                        2509,
                        2558,
                        2187,
                        2784,
                        2262,
                        2681,
                        2173,
                        2227,
                        2470,
                        2580,
                        2593,
                        1959,
                        2611,
                        2738,
                        2617,
                        2805,
                        2407,
                        2460,
                        2188,
                        2610,
                        2692,
                        2681,
                        2576,
                        2715,
                        1814,
                        2673,
                        2716,
                        2878,
                        2333,
                        2437,
                        2466,
                        2592,
                        2148,
                        2667,
                        2747,
                        2402,
                        2377,
                        2861,
                        2595,
                        2748,
                        2671,
                        2547,
                        2387,
                        2561,
                        2847,
                        2089,
                        2410,
                        2662,
                        2280,
                        2784,
                        2460,
                        2395,
                        2574,
                        2417,
                        2885,
                        2601,
                        2616,
                        2491,
                        2577,
                        2784,
                        2618,
                        2567,
                        2182,
                        2291,
                        2691,
                        2525,
                        2574,
                        2510,
                        2476,
                        2450,
                        2036,
                        2394,
                        2668,
                        2724,
                        2642,
                        2706,
                        2488,
                        2568,
                        2422,
                        2794,
                        2465,
                        2676,
                        2373,
                        2238,
                        2793,
                        2898,
                        2793,
                        2332,
                        2657,
                        2739,
                        2210,
                        2388,
                        2179,
                        2501,
                        2633,
                        2715,
                        2653,
                        2466,
                        2862,
                        2630,
                        2631,
                        2644,
                        2831,
                        2709,
                        2734,
                        2733,
                        2899,
                        2687,
                        2284,
                        2851,
                        2615,
                        2496,
                        2687,
                        2261,
                        2470,
                        2164,
                        2226,
                        2331,
                        2763,
                        2813,
                        2857,
                        2363,
                        2464,
                        2409,
                        2740,
                        2748,
                        2490,
                        2691,
                        2483,
                        2573,
                        2722,
                        2283,
                        2837,
                        2356,
                        2920,
                        2625,
                        2324,
                        2491,
                        2424,
                        2469,
                        2780,
                        2635,
                        2486,
                        2673,
                        2820,
                        2693,
                        2229,
                        2876,
                        2859,
                        2812,
                        2705,
                        2447,
                        2532,
                        2632,
                        2831,
                        2838,
                        2697,
                        2610,
                        2408,
                        2610,
                        2559,
                        2660,
                        2333,
                        2484,
                        2375,
                        2092,
                        2498,
                        2674,
                        2449,
                        2490,
                        2765,
                        2577,
                        2603,
                        2287,
                        2472,
                        2124,
                        2620,
                        2553,
                        2281,
                        2700,
                        2247,
                        2612,
                        2746,
                        2693,
                        2560,
                        2631,
                        2845,
                        2537,
                        2549,
                        2756,
                        2692,
                        2613,
                        2671,
                        2473,
                        2757,
                        2363,
                        2509,
                        2101,
                        2644,
                        1949,
                        2751,
                        2488,
                        2587,
                        2502,
                        2212,
                        2799,
                        2450,
                        2780,
                        2187,
                        2782,
                        2545,
                        2890,
                        2841,
                        2229,
                        2476,
                        2619,
                        2344,
                        2765,
                        2800,
                        2974,
                        2257,
                        2475,
                        2772,
                        2918,
                        2722,
                        2634,
                        2676,
                        2385,
                        2324,
                        2303,
                        2605,
                        2490,
                        2748,
                        2728,
                        2407,
                        2789,
                        2433,
                        2657,
                        2569,
                        2482,
                        2623,
                        2736,
                        2426,
                        2608,
                        2528
                    ],
                    "solution_final": {
                        "problem": {
                            "name": "NRH.5",
                            "points_number": 1000,
                            "reduced": false,
                            "subsets_number": 10000
                        },
                        "selected_subsets": [
                            182,
                            209,
                            409,
                            716,
                            1318,
                            1838,
                            2056,
                            2124,
                            2331,
                            2506,
                            2694,
                            2791,
                            3112,
                            3273,
                            3738,
                            3925,
                            4236,
                            4336,
                            4445,
                            4550,
                            4851,
                            6028,
                            6493,
                            6589,
                            7691,
                            8183,
                            8314,
                            8315,
                            8472,
                            8570,
                            8675,
                            9029,
                            9134,
                            9473
                        ]
                    },
                    "solve_config": {
                        "rwls_stopping_criterion": {
                            "steps": 150000,
                            "time": 1.8446744073709552e+19
                        },
                        "stopping_criterion": {
                            "generation": 100,
                            "rwls_cumulative_position": {
                                "steps": 18446744073709551615,
                                "time": 1.8446744073709552e+19
                            },
                            "time": 1.8446744073709552e+19
                        }
                    },
                    "wcrossover_operator": "min"
                }
            ]
        }
    ]
}