{
    "date": "2020-02-04T19:46:37Z",
    "git": {
        "head_sha1": "4c44acd41b3ef50cd836908a44eb2a98febbe3c1",
        "is_dirty": true,
        "retrieved_state": true
    },
    "instances": [
        {
            "greedy": {
                "solution_final": {
                    "problem": {
                        "name": "4.7",
                        "points_number": 200,
                        "reduced": false,
                        "subsets_number": 1000
                    },
                    "selected_subsets": [
                        1,
                        2,
                        27,
                        44,
                        49,
                        59,
                        60,
                        62,
                        65,
                        67,
                        83,
                        84,
                        103,
                        147,
                        151,
                        165,
                        171,
                        191,
                        192,
                        199,
                        204,
                        240,
                        294,
                        302,
                        327,
                        385,
                        472,
                        475,
                        600,
                        601,
                        624,
                        626,
                        680,
                        681,
                        691,
                        804,
                        847,
                        865,
                        875,
                        915,
                        937,
                        953,
                        985
                    ]
                },
                "time": 0.001765888
            },
            "instance": {
                "name": "4.7",
                "points_number": 200,
                "reduced": false,
                "subsets_number": 1000
            },
            "rwls": [
                {
                    "ended_at": {
                        "steps": 30000000,
                        "time": 32.467812608
                    },
                    "found_at": {
                        "steps": 3017,
                        "time": 0.030167552
                    },
                    "points_weights_final": [
                        42,
                        66,
                        63,
                        100,
                        87,
                        79,
                        106,
                        169,
                        81,
                        34,
                        48,
                        147,
                        143,
                        82,
                        93,
                        75,
                        116,
                        82,
                        83,
                        143,
                        108,
                        78,
                        96,
                        106,
                        98,
                        59,
                        76,
                        56,
                        94,
                        94,
                        116,
                        77,
                        77,
                        126,
                        68,
                        32,
                        42,
                        58,
                        98,
                        94,
                        102,
                        116,
                        62,
                        97,
                        108,
                        108,
                        55,
                        78,
                        77,
                        76,
                        105,
                        112,
                        105,
                        66,
                        34,
                        61,
                        84,
                        50,
                        102,
                        58,
                        126,
                        84,
                        122,
                        106,
                        72,
                        99,
                        132,
                        24,
                        93,
                        105,
                        87,
                        76,
                        56,
                        92,
                        46,
                        42,
                        54,
                        76,
                        100,
                        159,
                        128,
                        173,
                        88,
                        114,
                        68,
                        131,
                        87,
                        91,
                        148,
                        86,
                        55,
                        94,
                        131,
                        75,
                        70,
                        75,
                        34,
                        134,
                        146,
                        132,
                        83,
                        119,
                        98,
                        108,
                        76,
                        121,
                        99,
                        42,
                        112,
                        69,
                        73,
                        54,
                        78,
                        155,
                        112,
                        79,
                        88,
                        61,
                        70,
                        79,
                        83,
                        47,
                        103,
                        100,
                        55,
                        133,
                        46,
                        133,
                        62,
                        61,
                        105,
                        125,
                        108,
                        78,
                        72,
                        29,
                        90,
                        123,
                        62,
                        119,
                        46,
                        116,
                        84,
                        45,
                        98,
                        37,
                        52,
                        58,
                        93,
                        100,
                        108,
                        112,
                        97,
                        157,
                        124,
                        98,
                        128,
                        88,
                        74,
                        143,
                        106,
                        136,
                        104,
                        86,
                        142,
                        24,
                        46,
                        81,
                        96,
                        79,
                        47,
                        86,
                        92,
                        133,
                        102,
                        58,
                        44,
                        110,
                        68,
                        165,
                        111,
                        114,
                        86,
                        103,
                        116,
                        118,
                        95,
                        95,
                        99,
                        46,
                        89,
                        43,
                        97,
                        88,
                        90,
                        99,
                        112,
                        72,
                        96,
                        51
                    ],
                    "points_weights_initial": [
                        1,
                        1,
                        1,
                        1,
                        1,
                        1,
                        1,
                        1,
                        1,
                        1,
                        1,
                        1,
                        1,
                        1,
                        1,
                        1,
                        1,
                        1,
                        1,
                        1,
                        1,
                        1,
                        1,
                        1,
                        1,
                        1,
                        1,
                        1,
                        1,
                        1,
                        1,
                        1,
                        1,
                        1,
                        1,
                        1,
                        1,
                        1,
                        1,
                        1,
                        1,
                        1,
                        1,
                        1,
                        1,
                        1,
                        1,
                        1,
                        1,
                        1,
                        1,
                        1,
                        1,
                        1,
                        1,
                        1,
                        1,
                        1,
                        1,
                        1,
                        1,
                        1,
                        1,
                        1,
                        1,
                        1,
                        1,
                        1,
                        1,
                        1,
                        1,
                        1,
                        1,
                        1,
                        1,
                        1,
                        1,
                        1,
                        1,
                        1,
                        1,
                        1,
                        1,
                        1,
                        1,
                        1,
                        1,
                        1,
                        1,
                        1,
                        1,
                        1,
                        1,
                        1,
                        1,
                        1,
                        1,
                        1,
                        1,
                        1,
                        1,
                        1,
                        1,
                        1,
                        1,
                        1,
                        1,
                        1,
                        1,
                        1,
                        1,
                        1,
                        1,
                        1,
                        1,
                        1,
                        1,
                        1,
                        1,
                        1,
                        1,
                        1,
                        1,
                        1,
                        1,
                        1,
                        1,
                        1,
                        1,
                        1,
                        1,
                        1,
                        1,
                        1,
                        1,
                        1,
                        1,
                        1,
                        1,
                        1,
                        1,
                        1,
                        1,
                        1,
                        1,
                        1,
                        1,
                        1,
                        1,
                        1,
                        1,
                        1,
                        1,
                        1,
                        1,
                        1,
                        1,
                        1,
                        1,
                        1,
                        1,
                        1,
                        1,
                        1,
                        1,
                        1,
                        1,
                        1,
                        1,
                        1,
                        1,
                        1,
                        1,
                        1,
                        1,
                        1,
                        1,
                        1,
                        1,
                        1,
                        1,
                        1,
                        1,
                        1,
                        1,
                        1,
                        1,
                        1,
                        1,
                        1,
                        1,
                        1,
                        1,
                        1,
                        1,
                        1,
                        1,
                        1,
                        1,
                        1
                    ],
                    "solution_final": {
                        "problem": {
                            "name": "4.7",
                            "points_number": 200,
                            "reduced": false,
                            "subsets_number": 1000
                        },
                        "selected_subsets": [
                            24,
                            83,
                            173,
                            197,
                            198,
                            204,
                            240,
                            248,
                            258,
                            346,
                            363,
                            383,
                            406,
                            430,
                            441,
                            454,
                            465,
                            467,
                            491,
                            492,
                            538,
                            601,
                            613,
                            637,
                            670,
                            681,
                            683,
                            699,
                            772,
                            781,
                            784,
                            791,
                            793,
                            908,
                            910,
                            945,
                            959,
                            984
                        ]
                    },
                    "solution_initial": {
                        "problem": {
                            "name": "4.7",
                            "points_number": 200,
                            "reduced": false,
                            "subsets_number": 1000
                        },
                        "selected_subsets": [
                            1,
                            2,
                            27,
                            44,
                            49,
                            59,
                            60,
                            62,
                            65,
                            67,
                            83,
                            84,
                            103,
                            147,
                            151,
                            165,
                            171,
                            191,
                            192,
                            199,
                            204,
                            240,
                            294,
                            302,
                            327,
                            385,
                            472,
                            475,
                            600,
                            601,
                            624,
                            626,
                            680,
                            681,
                            691,
                            804,
                            847,
                            865,
                            875,
                            915,
                            937,
                            953,
                            985
                        ]
                    },
                    "stopping_criterion": {
                        "steps": 30000000,
                        "time": 1.8446744073709552e+19
                    }
                }
            ]
        }
    ]
}