{
    "date": "2019-12-06T11:31:09Z",
    "git": {
        "head_sha1": "fbd564bef73017f0ac7e3fc72cd61160df1f4256",
        "is_dirty": true,
        "retrieved_state": true
    },
    "instances": [
        {
            "greedy": {
                "solution_final": {
                    "problem": {
                        "name": "4.10",
                        "points_number": 200,
                        "reduced": false,
                        "subsets_number": 1000
                    },
                    "selected_subsets": [
                        7,
                        10,
                        16,
                        31,
                        44,
                        66,
                        106,
                        109,
                        116,
                        120,
                        139,
                        176,
                        190,
                        210,
                        212,
                        246,
                        261,
                        262,
                        269,
                        288,
                        298,
                        301,
                        353,
                        354,
                        379,
                        453,
                        454,
                        498,
                        517,
                        561,
                        620,
                        634,
                        635,
                        669,
                        682,
                        706,
                        726,
                        743,
                        774,
                        783,
                        897,
                        920,
                        944
                    ]
                },
                "time": 0.001918208
            },
            "instance": {
                "name": "4.10",
                "points_number": 200,
                "reduced": false,
                "subsets_number": 1000
            },
            "rwls": [
                {
                    "ended_at": {
                        "steps": 30000000,
                        "time": 52.166903552
                    },
                    "found_at": {
                        "steps": 8183,
                        "time": 0.112645888
                    },
                    "points_weights_final": [
                        238,
                        267,
                        148,
                        326,
                        180,
                        104,
                        229,
                        209,
                        82,
                        291,
                        165,
                        265,
                        138,
                        144,
                        117,
                        172,
                        193,
                        294,
                        239,
                        350,
                        234,
                        138,
                        249,
                        213,
                        227,
                        171,
                        270,
                        139,
                        212,
                        235,
                        240,
                        160,
                        293,
                        274,
                        247,
                        133,
                        296,
                        120,
                        199,
                        79,
                        315,
                        145,
                        131,
                        176,
                        88,
                        240,
                        203,
                        130,
                        175,
                        241,
                        194,
                        284,
                        332,
                        221,
                        280,
                        185,
                        275,
                        291,
                        314,
                        119,
                        171,
                        83,
                        222,
                        103,
                        293,
                        231,
                        288,
                        245,
                        326,
                        222,
                        211,
                        161,
                        185,
                        194,
                        349,
                        254,
                        150,
                        143,
                        311,
                        259,
                        163,
                        335,
                        150,
                        316,
                        276,
                        243,
                        459,
                        248,
                        213,
                        289,
                        186,
                        236,
                        305,
                        98,
                        257,
                        229,
                        246,
                        92,
                        286,
                        324,
                        233,
                        262,
                        300,
                        193,
                        203,
                        187,
                        195,
                        174,
                        294,
                        155,
                        340,
                        204,
                        84,
                        233,
                        312,
                        279,
                        246,
                        302,
                        268,
                        181,
                        197,
                        129,
                        259,
                        81,
                        275,
                        211,
                        323,
                        167,
                        263,
                        333,
                        250,
                        154,
                        248,
                        318,
                        337,
                        254,
                        237,
                        182,
                        340,
                        274,
                        309,
                        281,
                        161,
                        202,
                        149,
                        131,
                        312,
                        228,
                        269,
                        128,
                        332,
                        323,
                        86,
                        302,
                        152,
                        312,
                        235,
                        304,
                        208,
                        212,
                        301,
                        243,
                        210,
                        265,
                        268,
                        290,
                        141,
                        285,
                        180,
                        283,
                        274,
                        177,
                        253,
                        182,
                        120,
                        250,
                        147,
                        20,
                        274,
                        241,
                        111,
                        300,
                        141,
                        189,
                        360,
                        281,
                        231,
                        280,
                        254,
                        309,
                        175,
                        117,
                        201,
                        292,
                        232,
                        31,
                        144,
                        205,
                        168,
                        213
                    ],
                    "points_weights_initial": [
                        1,
                        1,
                        1,
                        1,
                        1,
                        1,
                        1,
                        1,
                        1,
                        1,
                        1,
                        1,
                        1,
                        1,
                        1,
                        1,
                        1,
                        1,
                        1,
                        1,
                        1,
                        1,
                        1,
                        1,
                        1,
                        1,
                        1,
                        1,
                        1,
                        1,
                        1,
                        1,
                        1,
                        1,
                        1,
                        1,
                        1,
                        1,
                        1,
                        1,
                        1,
                        1,
                        1,
                        1,
                        1,
                        1,
                        1,
                        1,
                        1,
                        1,
                        1,
                        1,
                        1,
                        1,
                        1,
                        1,
                        1,
                        1,
                        1,
                        1,
                        1,
                        1,
                        1,
                        1,
                        1,
                        1,
                        1,
                        1,
                        1,
                        1,
                        1,
                        1,
                        1,
                        1,
                        1,
                        1,
                        1,
                        1,
                        1,
                        1,
                        1,
                        1,
                        1,
                        1,
                        1,
                        1,
                        1,
                        1,
                        1,
                        1,
                        1,
                        1,
                        1,
                        1,
                        1,
                        1,
                        1,
                        1,
                        1,
                        1,
                        1,
                        1,
                        1,
                        1,
                        1,
                        1,
                        1,
                        1,
                        1,
                        1,
                        1,
                        1,
                        1,
                        1,
                        1,
                        1,
                        1,
                        1,
                        1,
                        1,
                        1,
                        1,
                        1,
                        1,
                        1,
                        1,
                        1,
                        1,
                        1,
                        1,
                        1,
                        1,
                        1,
                        1,
                        1,
                        1,
                        1,
                        1,
                        1,
                        1,
                        1,
                        1,
                        1,
                        1,
                        1,
                        1,
                        1,
                        1,
                        1,
                        1,
                        1,
                        1,
                        1,
                        1,
                        1,
                        1,
                        1,
                        1,
                        1,
                        1,
                        1,
                        1,
                        1,
                        1,
                        1,
                        1,
                        1,
                        1,
                        1,
                        1,
                        1,
                        1,
                        1,
                        1,
                        1,
                        1,
                        1,
                        1,
                        1,
                        1,
                        1,
                        1,
                        1,
                        1,
                        1,
                        1,
                        1,
                        1,
                        1,
                        1,
                        1,
                        1,
                        1,
                        1,
                        1,
                        1,
                        1,
                        1,
                        1,
                        1
                    ],
                    "solution_final": {
                        "problem": {
                            "name": "4.10",
                            "points_number": 200,
                            "reduced": false,
                            "subsets_number": 1000
                        },
                        "selected_subsets": [
                            3,
                            109,
                            116,
                            139,
                            193,
                            210,
                            269,
                            279,
                            288,
                            298,
                            308,
                            321,
                            322,
                            342,
                            364,
                            379,
                            416,
                            418,
                            453,
                            471,
                            498,
                            620,
                            634,
                            669,
                            701,
                            706,
                            726,
                            774,
                            799,
                            802,
                            818,
                            889,
                            903,
                            920,
                            933,
                            958,
                            986,
                            987
                        ]
                    },
                    "solution_initial": {
                        "problem": {
                            "name": "4.10",
                            "points_number": 200,
                            "reduced": false,
                            "subsets_number": 1000
                        },
                        "selected_subsets": [
                            7,
                            10,
                            16,
                            31,
                            44,
                            66,
                            106,
                            109,
                            116,
                            120,
                            139,
                            176,
                            190,
                            210,
                            212,
                            246,
                            261,
                            262,
                            269,
                            288,
                            298,
                            301,
                            353,
                            354,
                            379,
                            453,
                            454,
                            498,
                            517,
                            561,
                            620,
                            634,
                            635,
                            669,
                            682,
                            706,
                            726,
                            743,
                            774,
                            783,
                            897,
                            920,
                            944
                        ]
                    },
                    "stopping_criterion": {
                        "steps": 30000000,
                        "time": 1.8446744073709552e+19
                    }
                }
            ]
        }
    ]
}